paloma_sdk/__init__.py
paloma_sdk/client/__init__.py
paloma_sdk/client/lcd/__init__.py
paloma_sdk/client/lcd/api/__init__.py
paloma_sdk/client/lcd/api/_base.py
paloma_sdk/client/lcd/api/auth.py
paloma_sdk/client/lcd/api/authz.py
paloma_sdk/client/lcd/api/bank.py
paloma_sdk/client/lcd/api/cw20.py
paloma_sdk/client/lcd/api/cw721.py
paloma_sdk/client/lcd/api/distribution.py
paloma_sdk/client/lcd/api/feegrant.py
paloma_sdk/client/lcd/api/gov.py
paloma_sdk/client/lcd/api/ibc.py
paloma_sdk/client/lcd/api/ibc_transfer.py
paloma_sdk/client/lcd/api/mint.py
paloma_sdk/client/lcd/api/scheduler.py
paloma_sdk/client/lcd/api/skyway.py
paloma_sdk/client/lcd/api/slashing.py
paloma_sdk/client/lcd/api/staking.py
paloma_sdk/client/lcd/api/tendermint.py
paloma_sdk/client/lcd/api/tx.py
paloma_sdk/client/lcd/api/wasm.py
paloma_sdk/client/lcd/lcdclient.py
paloma_sdk/client/lcd/lcdutils.py
paloma_sdk/client/lcd/params.py
paloma_sdk/client/lcd/wallet.py
paloma_sdk/client/localpaloma.py
paloma_sdk/core/__init__.py
paloma_sdk/core/auth/__init__.py
paloma_sdk/core/auth/data/__init__.py
paloma_sdk/core/auth/data/account.py
paloma_sdk/core/auth/data/base_account.py
paloma_sdk/core/auth/data/base_vesting_account.py
paloma_sdk/core/auth/data/continuous_vesting_account.py
paloma_sdk/core/auth/data/delayed_vesting_account.py
paloma_sdk/core/auth/data/periodic_vesting_account.py
paloma_sdk/core/auth/msgs/__init__.py
paloma_sdk/core/auth/msgs/msg_create_periodic_vesting_account.py
paloma_sdk/core/auth/msgs/msg_create_vesting_account.py
paloma_sdk/core/auth/msgs/msg_donate_all_vesting_tokens.py
paloma_sdk/core/authz/__init__.py
paloma_sdk/core/authz/data.py
paloma_sdk/core/authz/msgs.py
paloma_sdk/core/bank/__init__.py
paloma_sdk/core/bank/msgs.py
paloma_sdk/core/bech32.py
paloma_sdk/core/block.py
paloma_sdk/core/broadcast.py
paloma_sdk/core/coin.py
paloma_sdk/core/coins.py
paloma_sdk/core/compact_bit_array.py
paloma_sdk/core/crisis/__init__.py
paloma_sdk/core/crisis/msgs.py
paloma_sdk/core/deposit.py
paloma_sdk-3.0.22.dist-info/LICENSE
paloma_sdk-3.0.22.dist-info/METADATA
paloma_sdk-3.0.22.dist-info/WHEEL
paloma_sdk-3.0.22.dist-info/RECORD
